pohw/__init__.py
pohw/api/__init__.py
pohw/api/ocr.py
pohw/api/ocr2excel.py
pohw/core/OCR.py
pohw/core/__init__.py
pohw/lib/CommonUtils.py
pohw/lib/Config.py
pohw/lib/Const.py
pohw/lib/__init__.py
pohw/lib/ocr_processor.py
pohw/lib/enums/FileTypeEnum.py
pohw/lib/enums/__init__.py
tests/__init__.py
tests/test_code/__init__.py
tests/test_code/test_init.py
tests/test_code/test_ocr.py
tests/test_code/test_ocr2excel.py
pohw-0.0.2.dist-info/LICENSE
pohw-0.0.2.dist-info/METADATA
pohw-0.0.2.dist-info/WHEEL
pohw-0.0.2.dist-info/top_level.txt
pohw-0.0.2.dist-info/RECORD
