Metadata-Version: 2.1
Name: pohw
Version: 0.0.2
Summary: pip install pohw
Home-page: https://www.python-office.com/
Author: CoderWanFeng
Author-email: 1957875073@qq.com
License: MIT
Project-URL: Bug Tracker, https://github.com/CoderWanFeng/pohw/issues
Project-URL: Documentation, https://github.com/CoderWanFeng/pohw/blob/main/README.md
Project-URL: Source Code, https://github.com/CoderWanFeng/pohw
Platform: any
Requires-Python: >=3.7
License-File: LICENSE
Requires-Dist: huaweicloudsdkocr
Requires-Dist: huaweicloudsdkcore
Requires-Dist: loguru
Requires-Dist: pofile
Requires-Dist: poprogress
Requires-Dist: pandas
